mcp_gaodeweather_server/__init__.py
mcp_gaodeweather_server/server.py
mcp_gaodeweather_server-0.1.2.dist-info/METADATA
mcp_gaodeweather_server-0.1.2.dist-info/WHEEL
mcp_gaodeweather_server-0.1.2.dist-info/entry_points.txt
mcp_gaodeweather_server-0.1.2.dist-info/RECORD
