Metadata-Version: 2.4
Name: mcp-gaodeweather-server
Version: 0.1.2
Summary: 这是一个使用高德地图的天气接口,获取当前城市天气的demo
Project-URL: Homepage, https://github.com/kevinkelin/mcp-gaodeweather-server
Project-URL: Issues, https://github.com/kevinkelin/mcp-gaodeweather-server/issues
Author-email: yangyanxing <yanxingyang@gmail.com>
Keywords: gaodeweather,mcp,server
Requires-Python: >=3.11
Requires-Dist: mcp[cli]>=1.5.0
